keras_trainer/__init__.py
keras_trainer/callbacks.py
keras_trainer/data_generators.py
keras_trainer/losses.py
keras_trainer/parallel.py
keras_trainer/regularizations.py
keras_trainer/run.py
keras_trainer/trainer.py
keras_trainer-1.2.5.dist-info/LICENSE
keras_trainer-1.2.5.dist-info/METADATA
keras_trainer-1.2.5.dist-info/WHEEL
keras_trainer-1.2.5.dist-info/top_level.txt
keras_trainer-1.2.5.dist-info/RECORD
